cannon/__init__.py
cannon/cli.py
cannon/main.py
cannon/main_exscript.py
cannon/main_pexpect.py
cannon-0.0.80.dist-info/LICENSE
cannon-0.0.80.dist-info/WHEEL
cannon-0.0.80.dist-info/METADATA
cannon-0.0.80.dist-info/RECORD
