Metadata-Version: 2.1
Name: cannon
Version: 0.0.80
Summary: An SSH automation tool based on Exscript
Home-page: https://github.com/mpenning/cannon
License: BSD-3-Clause
Keywords: SSH,Exscript
Author: Mike Pennington
Author-email: mike@pennington.net
Requires-Python: >=3.6
Classifier: Development Status :: 5 - Production/Stable
Classifier: Environment :: Plugins
Classifier: Intended Audience :: Developers
Classifier: Intended Audience :: Information Technology
Classifier: Intended Audience :: System Administrators
Classifier: Intended Audience :: Telecommunications Industry
Classifier: License :: OSI Approved :: BSD License
Classifier: License :: OSI Approved :: GNU General Public License (GPL)
Classifier: Natural Language :: English
Classifier: Operating System :: OS Independent
Classifier: Programming Language :: Python
Classifier: Programming Language :: Python :: 3
Classifier: Programming Language :: Python :: 3.10
Classifier: Programming Language :: Python :: 3.6
Classifier: Programming Language :: Python :: 3.7
Classifier: Programming Language :: Python :: 3.8
Classifier: Programming Language :: Python :: 3.9
Classifier: Topic :: Communications
Classifier: Topic :: Internet
Classifier: Topic :: Software Development :: Libraries :: Python Modules
Classifier: Topic :: System :: Networking
Classifier: Topic :: System :: Networking :: Monitoring
Requires-Dist: arrow (==1.2.1)
Requires-Dist: exscript (==2.6.3)
Requires-Dist: loguru (==0.5.3)
Requires-Dist: textfsm (==1.1.2)
Requires-Dist: traits (==6.3.2)
Project-URL: Documentation, http://www.pennington.net/py/cannon/
